{
    "properties":{
       "duty":{
          "properties":{
             "bans":{
                "type":"short"
             },
             "hours":{
                "type":"short"
             },
             "in_messages":{
                "type":"short"
             },
             "kicks":{
                "type":"short"
             },
             "minutes":{
                "type":"short"
             },
             "no_duty_time":{
                "type":"short"
             },
             "others":{
                "type":"short"
             },
             "out_messages":{
                "type":"short"
             },
             "warns":{
                "type":"short"
             },
             "zapytaj":{
                "type":"short"
             }
          }
       },
       "exit_reason":{
          "type":"keyword"
       }
    }
 }